borasem_waste/__init__.py
borasem_waste/auth.py
borasem_waste/borasem.py
borasem_waste/borasem_const.py
borasem_waste/pyproject.toml
borasem_waste/wastepickup.py
borasem_waste-0.0.15.dist-info/LICENSE.txt
borasem_waste-0.0.15.dist-info/METADATA
borasem_waste-0.0.15.dist-info/WHEEL
borasem_waste-0.0.15.dist-info/top_level.txt
borasem_waste-0.0.15.dist-info/RECORD
