Metadata-Version: 2.1
Name: borasem-waste
Version: 0.0.15
Summary: Get the next waste pickup schedule from Borås Energi och Miljö.
Home-page: https://github.com/danieloldberg/borasem-waste
Author: Daniel Oldberg
Author-email: daniel.oldberg@danieloldberg.se
License: MIT
Project-URL: Documentation, https://github.com/danieloldberg/borasem-waste
Project-URL: Source, https://github.com/danieloldberg/borasem-waste
Project-URL: Tracker, https://github.com/danieloldberg/borasem-waste/issues
Platform: any
Classifier: Development Status :: 4 - Beta
Classifier: Programming Language :: Python
Requires-Python: >=3.11
License-File: LICENSE.txt
Requires-Dist: aiohttp
Requires-Dist: importlib-metadata ; python_version < "3.8"
Provides-Extra: testing
Requires-Dist: setuptools ; extra == 'testing'
Requires-Dist: pytest ; extra == 'testing'
Requires-Dist: pytest-cov ; extra == 'testing'
